eyelinkparser/__init__.py
eyelinkparser/_events.py
eyelinkparser/_eyelinkparser.py
eyelinkparser/_traceprocessor.py
eyelinkparser/visualize.py
eyelinkparser-0.17.5.dist-info/COPYING
eyelinkparser-0.17.5.dist-info/WHEEL
eyelinkparser-0.17.5.dist-info/METADATA
eyelinkparser-0.17.5.dist-info/RECORD
