Metadata-Version: 2.1
Name: eyelinkparser
Version: 0.17.5
Summary: This file is part of eyelinkparser.
Keywords: data analysis,eye tracking,eyelink
Author-email: Sebastiaan Mathôt <s.mathot@cogsci.nl>
Requires-Python: >=3.7
Requires-Dist: datamatrix
Requires-Dist: fastnumbers
Project-URL: Documentation, https://github.com/open-cogsci/eyelinkparser
Project-URL: Source, https://github.com/open-cogsci/eyelinkparser
